github_action_publish-0.0.14.dist-info/METADATA
github_action_publish-0.0.14.dist-info/WHEEL
github_action_publish/__init__.py
github_action_publish/cli.py
github_action_publish-0.0.14.dist-info/RECORD
